{"questions":[{"questionTitle":"","anwers":["(A)","(B)","(C)"],"correctAnswer":1},{"questionTitle":"","anwers":["(A)","(B)","(C)"],"correctAnswer":0},{"questionTitle":"","anwers":["(A)","(B)","(C)"],"correctAnswer":2}],"script":"1). Who are you going to hire to remodel the building?\nYes, the center is still under construction.\nI'll probably go with Triple-J Contractors. \nYes, and there's a great view of the mountains.\n2). The copy machine on the third floor is out of order.\nOK, I'll have the service rep take a look at it. \nI'll order some more paper right away.\nWe should bring it back tomorrow.\n3). When did you finish testing the system?\nWe need to update the database.\nThe examination was really tough.\nAt about nine-thirty last night. "}