{"questions":[{"questionTitle":"","anwers":["(A)","(B)","(C)"],"correctAnswer":1},{"questionTitle":"","anwers":["(A)","(B)","(C)"],"correctAnswer":1},{"questionTitle":"","anwers":["(A)","(B)","(C)"],"correctAnswer":2}],"script":"1). Would you prefer an aisle seat or a window seat?\nYes, I would.\nI'd like to sit next to the aisle. \nI wanted the window.\n2). Where did you use to live?\nI live in Baltimore.\nI lived in Atlanta. \nI'll live in Cleveland.\n3). Why should we contract with your firm?\nYou shouldn't be able to.\nI'll sign the contract in the morning.\nOur service can't be beat. "}