{"questions":[{"questionTitle":"","anwers":["(A)","(B)","(C)"],"correctAnswer":1},{"questionTitle":"","anwers":["(A)","(B)","(C)"],"correctAnswer":1},{"questionTitle":"","anwers":["(A)","(B)","(C)"],"correctAnswer":0}],"script":"1). Wouldn't you rather telecommute?\nI will not like to.\nNo, I like working in an office. \nI'd not rather.\n2). Did you remember to bring your passport?\nYeah, I didn't.\nYes, I've got it right here. \nI forgot to brang it.\n3). Are we still on for Tuesday?\nWe sure are. At three. \nI'm off on Monday.\nNo, we weren't."}